README.rst
dependency.py
install.py
install_dependency.py
install_pip.py
setup.py
util.py
QuantDigger.egg-info/PKG-INFO
QuantDigger.egg-info/SOURCES.txt
QuantDigger.egg-info/dependency_links.txt
QuantDigger.egg-info/not-zip-safe
QuantDigger.egg-info/top_level.txt
demo/.DS_Store
demo/__init__.py
demo/manytomany.py
demo/mplot_demo.py
demo/plot_ma.py
demo/plot_strategy.py
demo/stock_search.py
quantdigger/.DS_Store
quantdigger/__init__.py
quantdigger/config.py
quantdigger/datastruct.py
quantdigger/errors.py
quantdigger.egg-info/SOURCES.txt
quantdigger/backup/backtest/mainwindow_ui.ui
quantdigger/backup/backtest/resource.qrc
quantdigger/backup/backtest/datasource/sina_format
quantdigger/backup/backtest/datasource/yahoo_format
quantdigger/backup/pyqt_kline/QuantView.py_bk
quantdigger/backup/pyqt_kline/_no_data.png
quantdigger/backup/pyqt_kline/readme
quantdigger/backup/zipline 2014-1-17/zipline2.pdf
quantdigger/backup/zipline 2014-1-17/zipline3.pdf
quantdigger/datasource/__init__.py
quantdigger/datasource/data.py
quantdigger/datasource/datautil.py
quantdigger/datasource/source.py
quantdigger/digger/.DS_Store
quantdigger/digger/__init__.py
quantdigger/digger/finance.py
quantdigger/digger/plotting.py
quantdigger/digger/sugar.py
quantdigger/engine/SHFE-IF000-Minutes-10.csv
quantdigger/engine/__init__.py
quantdigger/engine/api.py
quantdigger/engine/blotter.py
quantdigger/engine/context.py
quantdigger/engine/event.py
quantdigger/engine/exchange.py
quantdigger/engine/execute_unit.py
quantdigger/engine/orderedset.py
quantdigger/engine/qd.py
quantdigger/engine/series.py
quantdigger/images/new.png
quantdigger/images/print.png
quantdigger/images/save.png
quantdigger/images/undo.png
quantdigger/lib/TA_Lib-0.4.9-cp27-none-win_amd64.whl
quantdigger/technicals/.base.py.swp
quantdigger/technicals/__init__.py
quantdigger/technicals/base.py
quantdigger/technicals/common.py
quantdigger/util/__init__.py
quantdigger/util/progressbar.py
quantdigger/widgets/__init__.py
quantdigger/widgets/plugin_interface.py
quantdigger/widgets/widget_plot.py
quantdigger/widgets/mplotwidgets/__init__.py
quantdigger/widgets/mplotwidgets/mplots.py
quantdigger/widgets/mplotwidgets/stock_plot.py
