Metadata-Version: 1.1
Name: quantdigger
Version: 0.300
Summary: 量化交易PYTHON回测系统
Home-page: https://github.com/QuantFans/quantdigger
Author: QuantFans
Author-email: dingjie.wang@foxmail.com
License: MIT
Platform: UNKNOWN
Classifier: Development Status :: 3 - Alpha
Classifier: Intended Audience :: Developers
Classifier: License :: OSI Approved :: MIT License
Classifier: Operating System :: OS Independent
Classifier: Programming Language :: Python
